DovDetPa/__init__.py
DovDetPa/main.py
DovDetPa/timer.py
DovDetPa-0.1.0.dist-info/LICENCE.txt
DovDetPa-0.1.0.dist-info/METADATA
DovDetPa-0.1.0.dist-info/WHEEL
DovDetPa-0.1.0.dist-info/entry_points.txt
DovDetPa-0.1.0.dist-info/top_level.txt
DovDetPa-0.1.0.dist-info/RECORD
