Metadata-Version: 2.1
Name: DovDetPa
Version: 0.1.0
Summary: A package that waits for 5 minutes, returns a value, and uninstalls itself.
Home-page: https://github.com/yourusername/self_deleting_package
Author: Your Name
Author-email: your.email@example.com
Classifier: Programming Language :: Python :: 3
Classifier: License :: OSI Approved :: MIT License
Classifier: Operating System :: OS Independent
Requires-Python: >=3.6
License-File: LICENCE.txt
